SpringDataZhongwenBanben/README.md
SpringDataZhongwenBanben/__init__.py
SpringDataZhongwenBanben/__main__.py
SpringDataZhongwenBanben/file.epub
SpringDataZhongwenBanben/index.html
SpringDataZhongwenBanben/css/__init__.py
SpringDataZhongwenBanben/css/annotations.css
SpringDataZhongwenBanben/css/main.css
SpringDataZhongwenBanben/css/normalize.css
SpringDataZhongwenBanben/css/popup.css
SpringDataZhongwenBanben/font/__init__.py
SpringDataZhongwenBanben/font/fontello.eot
SpringDataZhongwenBanben/font/fontello.svg
SpringDataZhongwenBanben/font/fontello.ttf
SpringDataZhongwenBanben/font/fontello.woff
SpringDataZhongwenBanben/img/__init__.py
SpringDataZhongwenBanben/img/annotator-glyph-sprite.png
SpringDataZhongwenBanben/img/annotator-icon-sprite.png
SpringDataZhongwenBanben/img/apple-touch-icon.png
SpringDataZhongwenBanben/img/cancelfullscreen.png
SpringDataZhongwenBanben/img/close.png
SpringDataZhongwenBanben/img/fullscreen.png
SpringDataZhongwenBanben/img/loader.gif
SpringDataZhongwenBanben/img/menu-icon.png
SpringDataZhongwenBanben/img/save.png
SpringDataZhongwenBanben/img/saved.png
SpringDataZhongwenBanben/img/settings-s.png
SpringDataZhongwenBanben/img/settings.png
SpringDataZhongwenBanben/img/star.png
SpringDataZhongwenBanben/js/__init__.py
SpringDataZhongwenBanben/js/epub.js
SpringDataZhongwenBanben/js/epub.min.js
SpringDataZhongwenBanben/js/epub.min.map
SpringDataZhongwenBanben/js/hooks.min.js
SpringDataZhongwenBanben/js/hooks.min.map
SpringDataZhongwenBanben/js/reader.js
SpringDataZhongwenBanben/js/reader.js.map
SpringDataZhongwenBanben/js/reader.min.js
SpringDataZhongwenBanben/js/reader.min.map
SpringDataZhongwenBanben/js/hooks/__init__.py
SpringDataZhongwenBanben/js/hooks/extensions/__init__.py
SpringDataZhongwenBanben/js/hooks/extensions/highlight.js
SpringDataZhongwenBanben/js/libs/__init__.py
SpringDataZhongwenBanben/js/libs/jquery.min.js
SpringDataZhongwenBanben/js/libs/localforage.min.js
SpringDataZhongwenBanben/js/libs/screenfull.js
spring_data_zhongwen_banben-2024.3.4.0.dist-info/METADATA
spring_data_zhongwen_banben-2024.3.4.0.dist-info/WHEEL
spring_data_zhongwen_banben-2024.3.4.0.dist-info/entry_points.txt
spring_data_zhongwen_banben-2024.3.4.0.dist-info/top_level.txt
spring_data_zhongwen_banben-2024.3.4.0.dist-info/RECORD
